mufasa/__init__.py
mufasa/mufasa.py
mufasa_polimi-0.0.5.dist-info/LICENSE
mufasa_polimi-0.0.5.dist-info/METADATA
mufasa_polimi-0.0.5.dist-info/WHEEL
mufasa_polimi-0.0.5.dist-info/top_level.txt
mufasa_polimi-0.0.5.dist-info/RECORD
