Metadata-Version: 2.1
Name: mufasa-polimi
Version: 0.0.5
Summary: Utilities and Helpers for optimal usage of the MUFASA HPC cluster at Politecnico di Milano
Home-page: https://github.com/alberto-rota/mufasa
Author: Alberto Rota
Author-email: alberto1.rota@polimi.it
License: GPLv3
Classifier: Programming Language :: Python :: 3
Classifier: License :: OSI Approved :: GNU General Public License v3 (GPLv3)
Classifier: Operating System :: OS Independent
Requires-Python: >=3.6
License-File: LICENSE
